{
  "Enable": {
    "Value": false,
    "AttachedHotkey": {
      "ValueV2": {
        "ControllerKey": "None",
        "ControllerModifierKey": "None",
        "Key": "None",
        "Win": false
      }
    }
  },
  "Features": {
    "PoEModSwitch": {
      "Value": true,
      "AttachedHotkey": {
        "ValueV2": {
          "ControllerKey": "None",
          "ControllerModifierKey": "None",
          "Key": "None",
          "Win": false
        }
      }
    },
    "InventoryScanSwitch": {
      "Value": true,
      "AttachedHotkey": {
        "ValueV2": {
          "ControllerKey": "None",
          "ControllerModifierKey": "None",
          "Key": "None",
          "Win": false
        }
      }
    },
    "SkipQuadStash": {
      "Value": false,
      "AttachedHotkey": {
        "ValueV2": {
          "ControllerKey": "None",
          "ControllerModifierKey": "None",
          "Key": "None",
          "Win": false
        }
      }
    },
    "ShowOnlyT1Mods": {
      "Value": false,
      "AttachedHotkey": {
        "ValueV2": {
          "ControllerKey": "None",
          "ControllerModifierKey": "None",
          "Key": "None",
          "Win": false
        }
      }
    },
    "StashScanSwitch": {
      "Value": true,
      "AttachedHotkey": {
        "ValueV2": {
          "ControllerKey": "None",
          "ControllerModifierKey": "None",
          "Key": "None",
          "Win": false
        }
      }
    },
    "NPCVendorScanSwitch": {
      "Value": true,
      "AttachedHotkey": {
        "ValueV2": {
          "ControllerKey": "None",
          "ControllerModifierKey": "None",
          "Key": "None",
          "Win": false
        }
      }
    },
    "RitualScanSwitch": {
      "Value": true,
      "AttachedHotkey": {
        "ValueV2": {
          "ControllerKey": "None",
          "ControllerModifierKey": "None",
          "Key": "None",
          "Win": false
        }
      }
    },
    "Tier1Mod": "ffff00ff",
    "Tier2Mod": "00ff00ff",
    "Tier3Mod": "ff0000ff",
    "CharBGC": "000000e0"
  }
}